gliographseg/__init__.py
gliographseg/gliographseg.py
gliographseg/model.pth
gliographseg/model.py
gliographseg-0.1.2.dist-info/licenses/LICENSE
gliographseg-0.1.2.dist-info/METADATA
gliographseg-0.1.2.dist-info/WHEEL
gliographseg-0.1.2.dist-info/top_level.txt
gliographseg-0.1.2.dist-info/RECORD
