Metadata-Version: 2.4
Name: gliographseg
Version: 0.1.2
Summary: Graph-based brain tumor segmentation using superpixels and GNNs
Author: Salvatore Calderaro
License-Expression: MIT
Requires-Python: >=3.8
License-File: LICENSE
Requires-Dist: torch
Requires-Dist: torch-geometric
Requires-Dist: numpy
Requires-Dist: networkx
Requires-Dist: scikit-image
Requires-Dist: Pillow
Dynamic: license-file
